linkie/__init__.py
linkie/linkie.py
linkie-1.4.1.dist-info/LICENSE
linkie-1.4.1.dist-info/METADATA
linkie-1.4.1.dist-info/WHEEL
linkie-1.4.1.dist-info/entry_points.txt
linkie-1.4.1.dist-info/top_level.txt
linkie-1.4.1.dist-info/RECORD
