Metadata-Version: 2.1
Name: linkie
Version: 1.4.1
Summary: Linkie looks through files for broken links using Python 3.
Home-page: https://github.com/uccser/linkie
Author: University of Canterbury ComputerScience Education Research Group
Author-email: csse-education-research@canterbury.ac.nz
License: MIT
Keywords: link url checker
Platform: UNKNOWN
Classifier: Intended Audience :: Developers
Classifier: License :: OSI Approved :: MIT License
Classifier: Operating System :: MacOS :: MacOS X
Classifier: Operating System :: Microsoft :: Windows
Classifier: Operating System :: POSIX
Classifier: Programming Language :: Python :: 3
Classifier: Topic :: Text Processing :: Markup
Classifier: Topic :: Text Processing :: Markup :: HTML
Requires-Python: ~=3.4
Requires-Dist: PyYaml (==5.3.1)
Requires-Dist: requests (==2.22.0)
